{
  "$schema": "http://adaptivecards.io/schemas/adaptive-card.json",
  "type": "AdaptiveCard",
  "version": "1.0",
  "body": [
    {
      "type": "TextBlock",
      "text": "What country would you like to travel to?",
      "wrap": true
    },
    {
      "type": "TextBlock",
      "text": "*The following countries are currently supported.*",
      "wrap": true
    },
    {
      "type": "ColumnSet",
      "columns": [
        {
          "type": "Column",
          "width": "stretch",
          "items": [
            {
              "type": "ActionSet",
              "actions": [
                {
                  "type": "Action.Submit",
                  "title": "Netherlands",
                  "data": "Netherlands"
                }
              ]
            }
          ]
        },
        {
          "type": "Column",
          "width": "stretch",
          "items": [
            {
              "type": "ActionSet",
              "actions": [
                {
                  "type": "Action.Submit",
                  "title": "Italy",
                  "data": "Italy"
                }
              ]
            }
          ]
        },
        {
          "type": "Column",
          "width": "stretch",
          "items": [
            {
              "type": "ActionSet",
              "actions": [
                {
                  "type": "Action.Submit",
                  "title": "Germany",
                  "data": "Germany"
                }
              ]
            }
          ]
        }
      ]
    },
    {
      "type": "ColumnSet",
      "columns": [
        {
          "type": "Column",
          "width": "stretch",
          "items": [
            {
              "type": "ActionSet",
              "actions": [
                {
                  "type": "Action.Submit",
                  "title": "Spain",
                  "data": "Spain"
                }
              ]
            }
          ]
        },
        {
          "type": "Column",
          "width": "stretch",
          "items": [
            {
              "type": "ActionSet",
              "actions": [
                {
                  "type": "Action.Submit",
                  "title": "Greece",
                  "data": "Greece"
                }
              ]
            }
          ]
        },
        {
          "type": "Column",
          "width": "stretch",
          "items": [
            {
              "type": "ActionSet",
              "actions": [
                {
                  "type": "Action.Submit",
                  "title": "Morocco",
                  "data": "Morocco"
                }
              ]
            }
          ]
        }
      ]
    },
    {
      "type": "ColumnSet",
      "columns": [
        {
          "type": "Column",
          "width": "stretch",
          "items": [
            {
              "type": "ActionSet",
              "actions": [
                {
                  "type": "Action.Submit",
                  "title": "Austria",
                  "data": "Austria"
                }
              ]
            }
          ]
        },
        {
          "type": "Column",
          "width": "stretch",
          "items": [
            {
              "type": "ActionSet",
              "actions": [
                {
                  "type": "Action.Submit",
                  "title": "France",
                  "data": "France"
                }
              ]
            }
          ]
        },
        {
          "type": "Column",
          "width": "stretch",
          "items": [
            {
              "type": "ActionSet",
              "actions": [
                {
                  "type": "Action.Submit",
                  "title": "Great Britain",
                  "data": "Great Britain"
                }
              ]
            }
          ]
        }
      ]
    }
  ]
}